mavro/__init__.py
mavro/__main__.py
mavro/distbuilder/__init__.py
mavro/distbuilder/astral/__init__.py
mavro/distbuilder/astral/cli.py
mavro/internal/__init__.py
mavro/internal/build.py
mavro/internal/driver.py
mavro/internal/strap.py
mavro/parser/__init__.py
mavro/parser/coding.py
mavro/parser/lens.py
mavro/parser/lines.py
mavro/parser/packaging.py
mavro/pkg/__init__.py
mavro/pkg/console.py
mavro/pkg/integer.py
mavro/pkg/mesh2d.py
mavro/pkg/paint.py
mavro/pkg/remote.py
mavro/pkg/requiry.py
mavro/pkg/std.py
mavro/pkg/string.py
Mavro-0.12.dist-info/METADATA
Mavro-0.12.dist-info/WHEEL
Mavro-0.12.dist-info/entry_points.txt
Mavro-0.12.dist-info/top_level.txt
Mavro-0.12.dist-info/RECORD
