Metadata-Version: 2.1
Name: Mavro
Version: 0.12
Summary: An easy to understand language built from Python.
Author: astridot
Author-email: pixilreal@gmail.com
Classifier: Programming Language :: Python :: 3
Classifier: License :: OSI Approved :: GNU General Public License v3 (GPLv3)
Classifier: Operating System :: OS Independent
Requires-Python: >=3.12
Requires-Dist: pyinstaller
